elinor/__init__.py
elinor/ai/__init__.py
elinor/ai/model_summary.py
elinor/cv/__init__.py
elinor/cv/pil_str.py
elinor/data/__init__.py
elinor/data/convert.py
elinor/data/count_files.py
elinor/data/parser.py
elinor/data/string_matcher.py
elinor/data/youtube.py
elinor/dataset/PHOENIX_2014_T.py
elinor/dataset/__init__.py
elinor/loanlib/__init__.py
elinor/loanlib/loan_dotenv.py
elinor/misc/__init__.py
elinor/misc/timer.py
elinor-0.0.23.dist-info/licenses/LICENSE
elinor-0.0.23.dist-info/METADATA
elinor-0.0.23.dist-info/WHEEL
elinor-0.0.23.dist-info/top_level.txt
elinor-0.0.23.dist-info/RECORD
