Metadata-Version: 2.4
Name: elinor
Version: 0.0.23
Summary: some util functions
Author: Dashvvood
Author-email: mathismottis@gmail.com
License-File: LICENSE
Requires-Dist: numpy
Requires-Dist: tqdm
Requires-Dist: dotenv
Requires-Dist: deprecated
Dynamic: author
Dynamic: author-email
Dynamic: license-file
Dynamic: requires-dist
Dynamic: summary
